mxupy/IM.py
mxupy/Singleton.py
mxupy/__init__.py
mxupy/docGen.py
mxupy/hardware.py
mxupy/misc.py
mxupy/clipboard/__init__.py
mxupy/clipboard/misc.py
mxupy/decorator/__init__.py
mxupy/decorator/singleton.py
mxupy/decorator/user_lock.py
mxupy/disk/__init__.py
mxupy/disk/dir.py
mxupy/disk/file.py
mxupy/disk/zip.py
mxupy/media/__init__.py
mxupy/media/asr.py
mxupy/media/audio.py
mxupy/media/image.py
mxupy/media/ps.py
mxupy/media/video.py
mxupy/mp/Thr.py
mxupy/mp/ThrPool.py
mxupy/mp/__init__.py
mxupy/socket/TcpClient.py
mxupy/socket/__init__.py
mxupy/util/ArrayUtil.py
mxupy/util/ConfigUtil.py
mxupy/util/ConvertUtil.py
mxupy/util/CookieUtil.py
mxupy/util/DateTimeUtil.py
mxupy/util/ObjectUtil.py
mxupy/util/ProcessUtil.py
mxupy/util/RequestUtil.py
mxupy/util/ServerUtil.py
mxupy/util/StringUtil.py
mxupy/util/XmlUtil.py
mxupy/util/__init__.py
test/test1.py
test/test2.py
mxupy-1.0.18.dist-info/METADATA
mxupy-1.0.18.dist-info/WHEEL
mxupy-1.0.18.dist-info/top_level.txt
mxupy-1.0.18.dist-info/RECORD
