Metadata-Version: 2.4
Name: mxupy
Version: 1.0.18
Summary: An many/more extension/utils for python
Home-page: http://www.xtbeiyi.com/
Author: jerry1979
Author-email: jerry1979 <6018421@qq.com>
Project-URL: Homepage, http://www.xtbeiyi.com/
Dynamic: author
Dynamic: home-page
